streamlit_explorer/__init__.py
streamlit_explorer-0.1.0.dist-info/licenses/LICENSE
streamlit_explorer-0.1.0.dist-info/METADATA
streamlit_explorer-0.1.0.dist-info/WHEEL
streamlit_explorer-0.1.0.dist-info/top_level.txt
streamlit_explorer-0.1.0.dist-info/RECORD
