Metadata-Version: 2.4
Name: streamlit_explorer
Version: 0.1.0
Summary: A custom file and folder browser for Streamlit applications
Home-page: 
Author: Rezinski Oleg
Author-email: Rezinski Oleg <gitsoftmail@gmail.com>
License: MIT
Project-URL: Homepage, https://github.com/OlegRezinski/streamlit_explorer
Project-URL: Bug Reports, https://github.com/OlegRezinski/streamlit_explorer/issues
Project-URL: Source, https://github.com/OlegRezinski/streamlit_explorer
Keywords: streamlit,file-picker,folder-picker,directory-picker,file-browser,file-explorer,directory-explorer,folder-explorer
Classifier: Development Status :: 3 - Alpha
Classifier: Intended Audience :: Developers
Classifier: Topic :: Software Development :: Libraries :: Python Modules
Classifier: License :: OSI Approved :: MIT License
Classifier: Programming Language :: Python :: 3
Classifier: Programming Language :: Python :: 3.8
Classifier: Programming Language :: Python :: 3.9
Classifier: Programming Language :: Python :: 3.10
Classifier: Programming Language :: Python :: 3.11
Requires-Python: >=3.8
License-File: LICENSE
Requires-Dist: streamlit>=1.31.0
Dynamic: author
Dynamic: license-file
Dynamic: requires-python
